{"list_id":1038736711,"subject_urlified":"macbook_pro_13_pouce_750_go","publish_date":"2016-10-24","last_update_date":"2016-24-10","price":849,"store_id":"20206258","category_urlified":"multimedia","category_id":14,"subcategory_urlified":"informatique","subcategory_id":15,"zipcode":"73000","city_urlified":"chambery","region_urlified":"rhone_alpes","region_id":22,"department_urlified":"savoie","department_id":73,"part":true,"nb_picture":3,"options":{"booster":false,"daily_bump":false,"daily_bump30":false,"gallery":false,"gallery30":false,"ldv":false,"photosup":false,"sub_toplist":false,"urgent":false},"city":"Chambéry","department":"Toute la France","body":"Je vends mon MacBook Pro 13 pouce, 750 Go, version (mi-2012). Acheté en Janvier 2013. En très bon état. Écran 13,3 pouces (diagonale) Bicoeur Intel Core i7 2,9 GHz (turbo Boost jusqu'à 3,6)8 Go de mémoire Disque dur 750 GoAuteur 2,41 cmLargeur 32,5 cmProfondeur 22,7 cmPoids 2,06 kgGraphique Intel HD 4000 1536 MoCaméra FaceTime HD 720pSortie Mini DisplayPort nativePort d'alimentation MacSafePort Ethernet GigabitPort FireWire 800 2 ports USB 3Port ThunderboltEntrée/sortie ligne audioLecteur de carte SDXCFente câble antivol KensingtonSuperDrive 8xWi-fi Bluetooth 4.0(N'ésitez pas a me contacter par téléphone pour toute demande d'information ou photos supplémentaire)° Fourni avec boîte et câble d'alimentation d'origine.Excellent état aussi°\"Je ne réponds pas aux personnes qui me demande de répondre uniquement par e-mail, alors qu'ils me contacte par SMS\"Rigolos, mandat cash, etc ! Passer votre chemin...","subcategory":"Informatique","name":"christophe","subject":"MacBook Pro 13 pouce, 750 Go","images":["//img1.leboncoin.fr/ad-large/85b14aeff693d084fa97f2f7a855253542264dea.jpg","//img7.leboncoin.fr/ad-large/c0b0c8e45dcb6545eb74d171c5cb249c161c5532.jpg","//img3.leboncoin.fr/ad-image/ac5f5fc7a3bad2f31f6ef1e8756b0eaf2d2c328c.jpg"],"images_thumbs":["//img1.leboncoin.fr/ad-thumb/85b14aeff693d084fa97f2f7a855253542264dea.jpg","//img7.leboncoin.fr/ad-thumb/c0b0c8e45dcb6545eb74d171c5cb249c161c5532.jpg","//img3.leboncoin.fr/ad-thumb/ac5f5fc7a3bad2f31f6ef1e8756b0eaf2d2c328c.jpg"]}