{"list_id":1038736737,"subject_urlified":"pieces_ford_fusion_2007","publish_date":"2016-10-24","last_update_date":"2016-24-10","price":null,"store_id":"3736004","category_urlified":"vehicules","category_id":1,"subcategory_urlified":"equipement_auto","subcategory_id":6,"zipcode":"69700","region_urlified":"rhone_alpes","region_id":22,"department_urlified":"rhone","department_id":69,"part":true,"nb_picture":2,"options":{"booster":false,"daily_bump":false,"daily_bump30":false,"gallery":false,"gallery30":false,"ldv":false,"photosup":false,"sub_toplist":false,"urgent":false},"city":"","department":"Toute la France","body":"Vendre toutes les pièces Ford fusion voiture complète 1.4 TDCI ","subcategory":"Equipement Auto","name":"Massi69","subject":"pièces Ford fusion 2007","images":["//img4.leboncoin.fr/ad-large/cc4406cc18b82d161deb466355119948608d8399.jpg","//img2.leboncoin.fr/ad-large/cb3fb15e851a67873b66bdd2f13eadd05a9e3699.jpg"],"images_thumbs":["//img4.leboncoin.fr/ad-thumb/cc4406cc18b82d161deb466355119948608d8399.jpg","//img2.leboncoin.fr/ad-thumb/cb3fb15e851a67873b66bdd2f13eadd05a9e3699.jpg"]}